<?xml version="1.0" encoding="utf-8"?>
<!DOCTYPE pages SYSTEM "cellflash.dtd">

<!-- This file was generated by SCE. Do not edit. -->

<pages descr="multiplicate_20240417">

<page ismenu="false" volatile="false">
  <redirect src="dynerl://svc_variable:extract?%24(msisdn.)&amp;%5C%2B54%5C(.%2A%5C)&amp;packws&amp;msisdn&amp;%23(start)"/>
</page>

<page tag="(start)" descr="Servicios_Multiplicate_MenuPrincipal" ismenu="true" volatile="false" count="true">
<a href="#PromoKey9" key="1"> Multiplicate x 9 con GIGAS de Regalo!</a><br/>
<a href="#Promokey8" key="2"> Multiplicate x 8 con Megas de Regalo!</a><br/>
<a href="#Promokey7" key="3"> Multiplicate x 7 con Megas de Regalo!</a><br/>
<a href="#Promokey6" key="4"> Multiplicate x 6 con Megas de Regalo!</a><br/>
<a href="#Promokey4" key="5"> Multiplicate x 4 con Megas de Regalo!</a><br/>
<a href="#Promokey2" key="6"> Multiplicate x 2 con WhatsApp Gratis!</a>
</page>

<page tag="PromoKey9" ismenu="false" volatile="false" count="true">
<a href="#set_promokey_9"> Convertí $3800 en $34200 + 1 GB para Redes Sociales + 1GB  para que uses como quieras + Free Fire y WhatsApp Gratis TODO x 20 días.</a>
</page>

<page tag="Promokey2" ismenu="false" volatile="false" count="true">
<a href="#set_promokey_dosx2"> Convertí $650 en $1300 + WhatsApp Gratis x 1 día.</a>
</page>

<page tag="Promokey4" ismenu="false" volatile="false" count="true">
<a href="#set_promokey_4"> Convertí $1200 en $4800 + 50MB para redes sociales + WhatsApp Gratis x 3 días.</a>
</page>

<page tag="Promokey6" ismenu="false" volatile="false" count="true">
<a href="#set_promokey_6"> Convertí $1900 en $11400 + 100MB para redes sociales +WhatsApp Gratis x 5 días.</a>
</page>

<page tag="Promokey7" ismenu="false" volatile="false" count="true">
<a href="#set_promokey_7"> Convertí $2500 en $17500 + 500MB para Redes Sociales + 350MB  para que uses como quieras + Free Fire y WhatsApp Gratis TODO x 7 días.</a>
</page>

<page tag="Promokey8" ismenu="false" volatile="false" count="true">
<a href="#set_promokey_8"> Convertí $3000 en $24000 + 650MB para Redes Sociales + 500MB  para que uses como quieras + Free Fire y WhatsApp Gratis TODO x 10 días.</a>
</page>

<page tag="compra_multilpicate" ismenu="false" volatile="false">
  <redirect src="erl://svc_xml_generic:request?processOperationWs&amp;xml_generic&amp;packws&amp;%2Fpromogatewaysoap%2Fws&amp;processws&amp;10000&amp;ok=%23sms_ok,%3F=%23sms_ok"/>
</page>

<page tag="copy_of_set_promokey_7" ismenu="false" volatile="false">
  <redirect src="erl://svc_variable:set_v2?packws&amp;promokey&amp;%23compra_multilpicate&amp;Promo3456_KW_7_SIETE_CIETE_X7"/>
</page>

<page tag="set_promokey_4" ismenu="false" volatile="false">
  <redirect src="erl://svc_variable:set_v2?packws&amp;promokey&amp;%23compra_multilpicate&amp;Promo3456_KW_4_CUATRO_X4"/>
</page>

<page tag="set_promokey_6" ismenu="false" volatile="false">
  <redirect src="erl://svc_variable:set_v2?packws&amp;promokey&amp;%23compra_multilpicate&amp;Promo3456_KW_6_SEIS_CEIS_X6"/>
</page>

<page tag="set_promokey_7" ismenu="false" volatile="false">
  <redirect src="erl://svc_variable:set_v2?packws&amp;promokey&amp;%23compra_multilpicate&amp;Promo3456_KW_7_SIETE_CIETE_X7"/>
</page>

<page tag="set_promokey_8" ismenu="false" volatile="false">
  <redirect src="erl://svc_variable:set_v2?packws&amp;promokey&amp;%23compra_multilpicate&amp;Promo3456_KW_8_X8_OCHO_OHCO_8X"/>
</page>

<page tag="set_promokey_9" ismenu="false" volatile="false">
  <redirect src="erl://svc_variable:set_v2?packws&amp;promokey&amp;%23compra_multilpicate&amp;Promo3456_KW_9_X9_NUEVE"/>
</page>

<page tag="set_promokey_dosx2" ismenu="false" volatile="false">
  <redirect src="erl://svc_variable:set_v2?packws&amp;promokey&amp;%23compra_multilpicate&amp;Promo3456_KW_10_DIEZ_DIA_MULTI"/>
</page>

<page tag="sms_ok" descr="Servicios_Multiplicate_EnvioSMSok" ismenu="false" nav="end" volatile="false" count="true">
Tu solicitud esta siendo procesada, en breve recibiras un sms con mas informacion.
</page>


</pages>
